setup.py
ymci_ext_mail_alerts/__init__.py
ymci_ext_mail_alerts/mail.py
ymci_ext_mail_alerts/utils.py
ymci_ext_mail_alerts.egg-info/PKG-INFO
ymci_ext_mail_alerts.egg-info/SOURCES.txt
ymci_ext_mail_alerts.egg-info/dependency_links.txt
ymci_ext_mail_alerts.egg-info/entry_points.txt
ymci_ext_mail_alerts.egg-info/top_level.txt
ymci_ext_mail_alerts/mails/error.txt