Metadata-Version: 1.1
Name: ymci-ext-mail-alerts
Version: 1.1.0
Summary: Mail alert plugin for ymci
Home-page: UNKNOWN
Author: Jean-Marc Martins, Kozea
Author-email: jmartins@kozea.fr
License: UNKNOWN
Platform: Any
Provides: ymci_ext_mail_alerts
